.gitignore
Changes.rst
LICENSE
Makefile
README.rst
common.mk
setup.cfg
setup.py
aurora_data_api/__init__.py
aurora_data_api/exceptions.py
aurora_data_api/mysql_error_codes.py
docs/conf.py
docs/index.rst
preset_aurora_data_api.egg-info/PKG-INFO
preset_aurora_data_api.egg-info/SOURCES.txt
preset_aurora_data_api.egg-info/dependency_links.txt
preset_aurora_data_api.egg-info/requires.txt
preset_aurora_data_api.egg-info/top_level.txt
test/test.py